yamvp/__init__.py
yamvp/area_proportional_solver copy.py
yamvp/area_proportional_solver.py
yamvp/area_proportional_solver_COMPARE.py
yamvp/main copy.py
yamvp/main.py
yamvp/main_COMPARE.py
yamvp/sinus copy 2.py
yamvp/sinus copy.py
yamvp/sinus.py
yamvp-0.5.dist-info/licenses/LICENSE
yamvp-0.5.dist-info/METADATA
yamvp-0.5.dist-info/WHEEL
yamvp-0.5.dist-info/top_level.txt
yamvp-0.5.dist-info/RECORD
