Metadata-Version: 2.4
Name: yamvp
Version: 0.5
Summary: YAMVP - Yet Another Matplotlib Venn-diagram Plotter
Home-page: https://github.com/aielte-research/yamvp.git
Author: Bálint Csanády
Author-email: csbalint@protonmail.ch
License: MIT
Keywords: Venn,Venn diagram,Matplotlib,4 sets,5 sets,visualization,plotting,area-proportional
Classifier: Programming Language :: Python :: 3
Classifier: License :: OSI Approved :: MIT License
Classifier: Operating System :: OS Independent
Classifier: Topic :: Scientific/Engineering :: Mathematics
Requires-Python: >3.6
License-File: LICENSE
Requires-Dist: numpy
Requires-Dist: scipy
Requires-Dist: matplotlib
Requires-Dist: shapely
Dynamic: author
Dynamic: author-email
Dynamic: classifier
Dynamic: description
Dynamic: description-content-type
Dynamic: home-page
Dynamic: keywords
Dynamic: license
Dynamic: license-file
Dynamic: requires-dist
Dynamic: requires-python
Dynamic: summary
